<annotation>
    <folder>output</folder>
    <filename>rotated60_cnic5-06.jpg</filename>
    <path>/content/output/rotated60_cnic5-06.jpg</path>
    <source>
        <database>Unknown</database>
    </source>
    <size>
        <width>283</width>
        <height>178</height>
        <depth>3</depth>
    </size>
    <segmented>0</segmented>
    <object>
        <name>fname</name>
        <pose>Unspecified</pose>
        <truncated>0</truncated>
        <difficult>0</difficult>
        <bndbox>
            <xmin>218</xmin>
            <ymin>31</ymin>
            <xmax>244</xmax>
            <ymax>60</ymax>
        </bndbox>
    </object>    <object>
        <name>lname</name>
        <pose>Unspecified</pose>
        <truncated>0</truncated>
        <difficult>0</difficult>
        <bndbox>
            <xmin>187</xmin>
            <ymin>17</ymin>
            <xmax>217</xmax>
            <ymax>49</ymax>
        </bndbox>
    </object>    <object>
        <name>country</name>
        <pose>Unspecified</pose>
        <truncated>0</truncated>
        <difficult>0</difficult>
        <bndbox>
            <xmin>111</xmin>
            <ymin>64</ymin>
            <xmax>167</xmax>
            <ymax>129</ymax>
        </bndbox>
    </object>    <object>
        <name>id</name>
        <pose>Unspecified</pose>
        <truncated>0</truncated>
        <difficult>0</difficult>
        <bndbox>
            <xmin>134</xmin>
            <ymin>99</ymin>
            <xmax>179</xmax>
            <ymax>152</ymax>
        </bndbox>
    </object>    <object>
        <name>dob</name>
        <pose>Unspecified</pose>
        <truncated>0</truncated>
        <difficult>0</difficult>
        <bndbox>
            <xmin>89</xmin>
            <ymin>87</ymin>
            <xmax>123</xmax>
            <ymax>124</ymax>
        </bndbox>
    </object>
</annotation>
